{
  "A1": "A1 = \u2211 (brændselsmængde * emissionsfaktor) / 1000 med standardfaktorer for naturgas, diesel, fyringsolie og biogas.",
  "A2": "A2 = \u2211 (brændselsmængde * emissionsfaktor) / 1000. Kilometer registreres til intensitetsopfølgning.",
  "A3": "A3 = \u2211 (proces-output (ton) * emissionsfaktor (kg CO2e/ton)) / 1000 med standardfaktorer for cement, kalk, ammoniak og aluminium.",
  "A4": "Scope 1 flugtige emissioner = Σ (fyldning kg × lækageandel % × GWP100) ÷ 1.000.",
  "B1": "B1 = (el-forbrug * emissionsfaktor) - (el-forbrug * emissionsfaktor * (vedvarende% / 100) * 0.9)",
  "B2": "B2 = ((varmeforbrug - genindvinding) * emissionsfaktor) - ((varmeforbrug - genindvinding) * emissionsfaktor * (vedvarende% / 100) * 0.85)",
  "B3": "B3 = ((køleforbrug - frikøling) * emissionsfaktor) - ((køleforbrug - frikøling) * emissionsfaktor * (vedvarende% / 100) * 0.9)",
  "B4": "B4 = ((dampforbrug - genindvundet damp) * emissionsfaktor) - ((dampforbrug - genindvundet damp) * emissionsfaktor * (vedvarende% / 100) * 0.85)",
  "B5": "B5 = ((øvrigt energiforbrug - genindvundet energi) * emissionsfaktor) - ((øvrigt energiforbrug - genindvundet energi) * emissionsfaktor * (vedvarende% / 100) * 0.8)",
  "B6": "B6 = (elforbrug * nettab% / 100 * emissionsfaktor) - (elforbrug * nettab% / 100 * emissionsfaktor * (vedvarende% / 100) * 0.9)",
  "B7": "B7 = -(dokumenteret vedvarende el * dokumentationskvalitet% / 100 * 0.95 * residual emissionsfaktor)",
  "B8": "B8 = -((egenproduceret vedvarende el - eksport) * dokumentationskvalitet% / 100 * 0.9 * residual emissionsfaktor)",
  "B9": "B9 = -(min(PPA-leveret el, matchet forbrug) * (1 - nettab% / 100) * dokumentationskvalitet% / 100 * 0.92 * residual emissionsfaktor)",
  "B10": "B10 = -(min(PPA-kontrakteret el, matchet forbrug) * finansiel dækning% / 100 * dokumentationskvalitet% / 100 * 0.88 * residual emissionsfaktor)",
  "B11": "B11 = -(min(certifikater, matchet forbrug) * timekorrelation% / 100 * 0.9 * dokumentationskvalitet% / 100 * 0.85 * residual emissionsfaktor)",
  "C1": "C1 = ansatte * pendlerdage/uge * uger/år * (1 - fjernarbejde% / 100) * tur-retur distance * emissionsfaktor / 1000",
  "C2": "C2 = (((fly km * fly faktor) + (tog km * tog faktor) + (vej km * vej faktor)) * (1 - virtuelle møder% / 100) + (hotel nætter * hotel faktor)) / 1000",
  "C3": "C3 = (((el kWh * el upstream faktor) * (1 + nettab% / 100) * (1 - vedvarende% / 100 * 0.8)) + (brændstof kWh * brændstof upstream faktor)) / 1000",
  "C4": "C4 = ((vej tkm * vej faktor) + (bane tkm * bane faktor) + (sø tkm * sø faktor) + (luft tkm * luft faktor)) * (1 - (konsolidering% / 100 * 0.6 + lavemission% / 100 * 0.75)) / 1000",
  "C5": "C5 = ((deponi ton * deponi faktor) + (forbrænding ton * forbrænding faktor) + (kompost ton * kompost faktor) + (genanvendelse ton * genanvendelse faktor)) * (1 - (genvinding% / 100 * 0.7 + genbrugsandel% / 100 * 0.8)) / 1000",
  "C6": "C6 = (((areal * el-intensitet) * lejer% / 100 * (1 - fælles% / 100) * el faktor * (1 - vedvarende el% / 100 * 0.75)) + ((areal * varme-intensitet) * lejer% / 100 * (1 - fælles% / 100) * varme faktor * (1 - vedvarende varme% / 100 * 0.6))) / 1000",
  "C7": "C7 = (((vej tkm * vej faktor) * (1 - lavemissionsandel% / 100 * 0.7)) + (bane tkm * bane faktor) + (sø tkm * sø faktor) + (luft tkm * luft faktor) + (lager kWh * lager faktor * (1 - vedvarende lager% / 100 * 0.85))) / 1000",
  "C8": "C8 = (((areal * el-intensitet) * udnyttelse% / 100 * udlejeransvar% / 100 * (1 - effektivisering% / 100 * 0.9) * el faktor * (1 - vedvarende el% / 100 * 0.85)) + ((areal * varme-intensitet) * udnyttelse% / 100 * udlejeransvar% / 100 * (1 - effektivisering% / 100 * 0.9) * varme faktor * (1 - vedvarende varme% / 100 * 0.85))) / 1000",
  "C9": "C9 = (tonnage * energiintensitet * (1 - effektivisering% / 100 * 0.85) * (1 - sekundært materiale% / 100 * 0.6) * emissionsfaktor * (1 - vedvarende energi% / 100 * 0.9)) / 1000",
  "C10": "Scope 3 upstream leasede aktiver: energi fra indtastet kWh eller areal × standardintensitet multipliceres med emissionsfaktoren for den valgte energitype.",
  "C11": "Scope 3 downstream leasede aktiver: energi fra indtastet kWh eller areal × standardintensitet multipliceres med emissionsfaktoren for den valgte energitype.",
  "C12": "Scope 3 franchising: Σ (omsætning × kg CO₂e/DKK eller energiforbrug × kg CO₂e/kWh) konverteret til ton CO₂e.",
  "C13": "Scope 3 investeringer: Σ (investeret beløb × emissionsintensitet i kg CO₂e/DKK) konverteret til ton CO₂e.",
  "C14": "C14 = \u2211 (tonnage * emissionsfaktor (kg CO2e/ton)) / 1000 med standardværdier for genanvendelse, forbrænding og deponi.",
  "C15": "Scope 3 screening: Σ (estimeret mængde × valgt emissionsfaktor) / 1000 for de relevante kategorier.",
  "D1": "D1 governance-score = gennemsnit af seks governance-dimensioner (organisatorisk afgrænsning, Scope 2 metode, Scope 3 screening, datakvalitet, væsentlighed og strategi) × 100."
}
